opqua/__init__.py
opqua/model.py
opqua/analysis/__init__.py
opqua/analysis/data.py
opqua/analysis/plot.py
opqua/internal/__init__.py
opqua/internal/data.py
opqua/internal/host.py
opqua/internal/intervention.py
opqua/internal/landscape.py
opqua/internal/plot.py
opqua/internal/population.py
opqua/internal/setup.py
opqua/internal/simulation.py
opqua/internal/vector.py
opqua/parameters/__init__.py
opqua/parameters/host-host.csv
opqua/parameters/vector-borne.csv
opqua-1.2.1.dist-info/LICENSE
opqua-1.2.1.dist-info/METADATA
opqua-1.2.1.dist-info/WHEEL
opqua-1.2.1.dist-info/top_level.txt
opqua-1.2.1.dist-info/RECORD
